streamlit_ttyd/__init__.py
streamlit_ttyd/binary/ttyd.aarch64
streamlit_ttyd/binary/ttyd.arm
streamlit_ttyd/binary/ttyd.win32.exe
streamlit_ttyd/binary/ttyd.x86_64
streamlit_ttyd-0.2.0.dist-info/LICENSE
streamlit_ttyd-0.2.0.dist-info/WHEEL
streamlit_ttyd-0.2.0.dist-info/METADATA
streamlit_ttyd-0.2.0.dist-info/RECORD
