Metadata-Version: 2.3
Name: streamlit-ttyd
Version: 0.2.0
Summary: This module provides a way to use a terminal under streamlit framework
Author-email: Sampad B Mohanty <smpdmohanty@gmail.com>
Classifier: License :: OSI Approved :: MIT License
Requires-Dist: streamlit
Requires-Dist: port-for
Requires-Dist: psutil
Project-URL: Homepage, https://github.com/NeveIsa/streamlit_ttyd
